agemcp/.env.example
agemcp/__init__.py
agemcp/ag_edge.py
agemcp/ag_edges.py
agemcp/ag_entity.py
agemcp/ag_graph.py
agemcp/ag_mutation.py
agemcp/ag_patch.py
agemcp/ag_properties.py
agemcp/ag_query_builder.py
agemcp/ag_vertex.py
agemcp/ag_vertices.py
agemcp/apache_age.py
agemcp/cli.py
agemcp/data_source_name.py
agemcp/database_connection_settings.py
agemcp/db.py
agemcp/environment.py
agemcp/list_root_model.py
agemcp/lru_cache.py
agemcp/query_string_codec.py
agemcp/royal_description.py
agemcp/server.py
agemcp/settings.py
agemcp/utils.py
agemcp-0.5.3.dist-info/METADATA
agemcp-0.5.3.dist-info/WHEEL
agemcp-0.5.3.dist-info/entry_points.txt
agemcp-0.5.3.dist-info/licenses/LICENSE
agemcp-0.5.3.dist-info/RECORD
