Metadata-Version: 2.4
Name: agemcp
Version: 0.5.3
Summary: PostgreSQL MCP
Author: veloper
License-File: LICENSE
Requires-Python: >=3.11
Requires-Dist: asyncpg>=0.30.0
Requires-Dist: beautifulsoup4>=4.13.4
Requires-Dist: blinker>=1.9.0
Requires-Dist: click>=8.2.1
Requires-Dist: dotenv>=0.9.9
Requires-Dist: fastmcp>=2.8.1
Requires-Dist: httpx>=0.28.1
Requires-Dist: nanoid>=2.0.0
Requires-Dist: networkx>=3.5
Requires-Dist: numpy<2,>=1.26.4
Requires-Dist: pydantic-settings>=2.9.1
Requires-Dist: pydantic>=2.11.7
Requires-Dist: pyvis>=0.3.2
Requires-Dist: requests>=2.32.4
Requires-Dist: sh>=2.2.2
Requires-Dist: snakeviz>=2.2.2
Requires-Dist: sqlalchemy-utils>=0.41.2
Requires-Dist: sqlalchemy[asyncio]>=2.0.41
